CHANGES.rst
DESCRIPTION.rst
MANIFEST.in
README.md
setup.py
src/simple_mask_utils.egg-info/PKG-INFO
src/simple_mask_utils.egg-info/SOURCES.txt
src/simple_mask_utils.egg-info/dependency_links.txt
src/simple_mask_utils.egg-info/requires.txt
src/simple_mask_utils.egg-info/top_level.txt
src/smu/__init__.py
src/smu/_masks.py